{"name":"build-javascript","namedChunkGroups":{"app":{"name":"app","assets":[{"name":"webpack-runtime-144592fec1241018ec1d.js","size":3950},{"name":"framework-9d608f77b5c9a88afabd.js","size":140350},{"name":"styles.9e907bc32054b7771552.css","size":1245},{"name":"app-8200a6777df397f85873.js","size":97291}],"filteredAssets":0,"assetsSize":242836,"filteredAuxiliaryAssets":3,"auxiliaryAssetsSize":763889},"component---src-pages-404-tsx":{"name":"component---src-pages-404-tsx","assets":[{"name":"commons-f8d90a1716150c1a345e.js","size":21811},{"name":"component---src-pages-404-tsx-36db6f73a4f925d8624b.js","size":1272}],"filteredAssets":0,"assetsSize":23083,"filteredAuxiliaryAssets":2,"auxiliaryAssetsSize":86092},"component---src-pages-index-tsx":{"name":"component---src-pages-index-tsx","assets":[{"name":"c16184b3-dd7f3e8691089e3d1af3.js","size":688},{"name":"commons-f8d90a1716150c1a345e.js","size":21811},{"name":"component---src-pages-index-tsx-7bff2b4506db5671d30e.js","size":120858}],"filteredAssets":0,"assetsSize":143357,"filteredAuxiliaryAssets":3,"auxiliaryAssetsSize":1467640}},"assetsByChunkName":{"app":["webpack-runtime-144592fec1241018ec1d.js","framework-9d608f77b5c9a88afabd.js","styles.9e907bc32054b7771552.css","app-8200a6777df397f85873.js"],"component---src-pages-404-tsx":["commons-f8d90a1716150c1a345e.js","component---src-pages-404-tsx-36db6f73a4f925d8624b.js"],"component---src-pages-index-tsx":["c16184b3-dd7f3e8691089e3d1af3.js","commons-f8d90a1716150c1a345e.js","component---src-pages-index-tsx-7bff2b4506db5671d30e.js"]},"childAssetsByChunkName":{}}